chibp/__init__.py
chibp/api.py
chibp-1.3.1.dist-info/LICENSE
chibp-1.3.1.dist-info/METADATA
chibp-1.3.1.dist-info/WHEEL
chibp-1.3.1.dist-info/top_level.txt
chibp-1.3.1.dist-info/RECORD
