Metadata-Version: 2.1
Name: chibp
Version: 1.3.1
Summary: A package for utilising the Haveibeenpwned API
Home-page: https://github.com/chrisdunne/hibp
Author: Christopher Dunne
Author-email: contact@chrisdunne.net
License: UNKNOWN
Platform: UNKNOWN
Classifier: Programming Language :: Python :: 3
Classifier: License :: OSI Approved :: MIT License
Classifier: Operating System :: OS Independent
Requires-Dist: requests
